dynpi-1.0.3.dist-info/licenses/LICENSE
dynpy/__init__.py
dynpy/continuous.py
dynpy/dynamics.py
dynpy/random_description.py
dynpy/trainmodels.py
dynpy/models/__init__.py
dynpy/models/continuous.py
dynpy/models/ddof.py
dynpy/models/elements.py
dynpy/models/mdof.py
dynpy/models/sdof.py
dynpy/models/systems.py
dynpy/models/control/__init__.py
dynpy/models/control/controllers.py
dynpy/models/electric/__init__.py
dynpy/models/electric/battery.py
dynpy/models/electric/car.py
dynpy/models/electric/elements.py
dynpy/models/electric/motor.py
dynpy/models/electric/vehicle.py
dynpy/models/mechanics/__init__.py
dynpy/models/mechanics/absorber.py
dynpy/models/mechanics/absorbers.py
dynpy/models/mechanics/bike.py
dynpy/models/mechanics/bridge.py
dynpy/models/mechanics/car.py
dynpy/models/mechanics/chair.py
dynpy/models/mechanics/disk.py
dynpy/models/mechanics/disks.py
dynpy/models/mechanics/engine.py
dynpy/models/mechanics/gears.py
dynpy/models/mechanics/motorcoach.py
dynpy/models/mechanics/offshore.py
dynpy/models/mechanics/pendulum.py
dynpy/models/mechanics/principles.py
dynpy/models/mechanics/projectile.py
dynpy/models/mechanics/shaft.py
dynpy/models/mechanics/skyscraper.py
dynpy/models/mechanics/tensioner.py
dynpy/models/mechanics/tmac.py
dynpy/models/mechanics/tmd.py
dynpy/models/mechanics/trolley.py
dynpy/models/mechanics/trolleys.py
dynpy/models/mechanics/vehicle.py
dynpy/models/mechanics/wheelchairs_TEMP.py
dynpy/models/mechanics/test/test.py
dynpy/models/odes/__init__.py
dynpy/models/odes/linear.py
dynpy/models/odes/nonlinear.py
dynpy/models/odes/numerical.py
dynpy/solvers/__init__.py
dynpy/solvers/linear.py
dynpy/solvers/nonlinear.py
dynpy/solvers/numerical.py
dynpy/solvers/perturbational.py
dynpy/solvers/reliability.py
dynpy/solvers/tools.py
dynpy/utilities/__init__.py
dynpy/utilities/adaptable.py
dynpy/utilities/cloning.py
dynpy/utilities/creators.py
dynpy/utilities/report.py
dynpy/utilities/timeseries.py
dynpy/utilities/tools.py
dynpy/utilities/components/__init__.py
dynpi-1.0.3.dist-info/METADATA
dynpi-1.0.3.dist-info/WHEEL
dynpi-1.0.3.dist-info/top_level.txt
dynpi-1.0.3.dist-info/RECORD
