Metadata-Version: 2.4
Name: DynPi
Version: 1.0.3
Summary: DynPy is a Python module designed for engineering calculations on dynamical systems. It provides a comprehensive framework for modeling, simulating, and analyzing dynamic mechanical systems.
Author-email: Bogumił Chiliński <bogumil.chilinski@gmail.com>
License: MIT License
Project-URL: repository, https://github.com/bogumilchilinski/dynpy/?tab=readme-ov-file#introduction
Requires-Python: >=3.8
License-File: LICENSE
Requires-Dist: numpy>=1.26.0
Requires-Dist: pylatex>=1.4.2
Requires-Dist: sympy>=1.12
Requires-Dist: pandas>=2.1.0
Requires-Dist: matplotlib>=3.8.0
Requires-Dist: scipy>=1.11.0
Requires-Dist: pint>=0.23
Requires-Dist: pypandoc>=1.12
Requires-Dist: wand>=0.6.11
Dynamic: license-file
